{
    "Teams": [{
        "stillingame": "True",
        "uniqueid": 1,
        "Players": "Khaladji Emma/Maouhoub Quentin"
    }, {
        "stillingame": "True",
        "uniqueid": 2,
        "Players": "Florent /Shmavosaure Brown"
    }, {
        "stillingame": "True",
        "uniqueid": 3,
        "Players": "Sam Ahizi/Girex"
    }, {
        "stillingame": "True",
        "uniqueid": 4,
        "Players": "Corne Hugo/Del Cerro Mathias"
    }, {
        "stillingame": "True",
        "uniqueid": 5,
        "Players": "Besson maxime/Ugo"
    }, {
        "stillingame": "True",
        "uniqueid": 6,
        "Players": "Lavanant Mathieu/Faure Béranger "
    }, {
        "stillingame": "True",
        "uniqueid": 7,
        "Players": "Vice gros cuisseau /Tonton Toinou"
    }, {
        "stillingame": "True",
        "uniqueid": 8,
        "Players": "Guibra/Lapinou"
    }]
}